mantis_sdk/__init__.py
mantis_sdk/client.py
mantis_sdk/exceptions.py
mantis_sdk/utils.py
Mantis_SDK-1.0.0.dist-info/LICENSE
Mantis_SDK-1.0.0.dist-info/METADATA
Mantis_SDK-1.0.0.dist-info/WHEEL
Mantis_SDK-1.0.0.dist-info/top_level.txt
Mantis_SDK-1.0.0.dist-info/RECORD
