Metadata-Version: 2.1
Name: Mantis-SDK
Version: 1.0.0
Summary: SDK for interacting with the Mantis API
Home-page: https://github.com/KellisLab/Mantis_SDK
Author: Sufian A
Author-email: 
License: UNKNOWN
Platform: UNKNOWN
Requires-Python: >=3.7
License-File: LICENSE
Requires-Dist: requests
